sargon/__init__.py
sargon/data.py
sargon/engines.py
sargon-0.0.1.dist-info/WHEEL
sargon-0.0.1.dist-info/METADATA
sargon-0.0.1.dist-info/RECORD
