Metadata-Version: 2.1
Name: sargon
Version: 0.0.1
Summary: A random generator of codes, names and other words
Home-page: https://github.com/santiagobasulto/sargon
License: MIT
Author: Santiago Basulto
Author-email: santiago.basulto@gmail.com
Requires-Python: >=3.8,<4.0
Classifier: License :: OSI Approved :: MIT License
Classifier: Programming Language :: Python :: 3
Classifier: Programming Language :: Python :: 3.8
Project-URL: Documentation, https://github.com/santiagobasulto/sargon
Project-URL: Repository, https://github.com/santiagobasulto/sargon
